.gitignore
MANIFEST.in
README.rst
bootstrap.py
buildout.cfg
setup.cfg
setup.py
docs/changes.rst
potools/__init__.py
potools/pocheck.py
potools/podiff.py
potools/poget.py
potools/popopulate.py
potools/pounique.py
potools/poupdate.py
potools/utils.py
potools.egg-info/PKG-INFO
potools.egg-info/SOURCES.txt
potools.egg-info/dependency_links.txt
potools.egg-info/entry_points.txt
potools.egg-info/not-zip-safe
potools.egg-info/requires.txt
potools.egg-info/top_level.txt
potools/tests/__init__.py
potools/tests/test_pocheck.py
potools/tests/test_podiff.py
potools/tests/test_poget.py
potools/tests/test_pounique.py
potools/tests/test_poupdate.py
potools/tests/test_setup.py
potools/tests/locales/test.po
potools/tests/locales/test.pot
potools/tests/locales2/test.po