Metadata-Version: 1.0
Name: potools
Version: 0.3.2
Summary: Python scripts to help with managing translations
Home-page: http://syslab.com
Author: Lennart Regebro, Wolfgang Thomas, Manuel Reinhardt, JC Brand
Author-email: info@syslab.com
License: GPL
Platform: UNKNOWN
